functionc.cp39-win_amd64.pyd
topic_cluster_visualizer/__init__.py
topic_cluster_visualizer/plots.py
topic_cluster_visualizer/topicclustervisualizer.py
topic_cluster_visualizer/utils.py
topic_cluster_visualizer-0.2.dist-info/METADATA
topic_cluster_visualizer-0.2.dist-info/WHEEL
topic_cluster_visualizer-0.2.dist-info/top_level.txt
topic_cluster_visualizer-0.2.dist-info/RECORD
