Metadata-Version: 2.1
Name: topic-cluster-visualizer
Version: 0.2
Summary: UNKNOWN
Home-page: https://github.com/lyric2249/topicclustervisualizer
License: UNKNOWN
Platform: UNKNOWN
Requires-Dist: plotly (>=4.14.3)
Requires-Dist: factor-analyzer (>=0.4.0)
